mindbot/__init__.py
mindbot/ai_functions.py
mindbotai-0.1.dist-info/LICENSE
mindbotai-0.1.dist-info/METADATA
mindbotai-0.1.dist-info/WHEEL
mindbotai-0.1.dist-info/top_level.txt
mindbotai-0.1.dist-info/RECORD
