Metadata-Version: 2.1
Name: mindbotai
Version: 0.1
Summary: MindBot AI Functions Package
Home-page: https://github.com/AetherMind-Ai/mindbotlibrary
Author: Ahmed Helmy Ali Eletr
Author-email: ahmedhelmyali.dev@gmail.com
Classifier: Programming Language :: Python :: 3
Classifier: License :: OSI Approved :: MIT License
Classifier: Operating System :: OS Independent
License-File: LICENSE
Requires-Dist: google-generativeai
Requires-Dist: httpx
